LICENSE
MANIFEST.in
README.rst
requirements.txt
requirements_dev.txt
setup.cfg
setup.py
tests.sh
pathspider/__init__.py
pathspider/base.py
pathspider/desync.py
pathspider/forge.py
pathspider/observer.py
pathspider/single.py
pathspider/sync.py
pathspider.egg-info/PKG-INFO
pathspider.egg-info/SOURCES.txt
pathspider.egg-info/dependency_links.txt
pathspider.egg-info/entry_points.txt
pathspider.egg-info/requires.txt
pathspider.egg-info/top_level.txt
pathspider/chains/__init__.py
pathspider/chains/base.py
pathspider/chains/basic.py
pathspider/chains/dns.py
pathspider/chains/dscp.py
pathspider/chains/ecn.py
pathspider/chains/evil.py
pathspider/chains/icmp.py
pathspider/chains/mss.py
pathspider/chains/noop.py
pathspider/chains/tcp.py
pathspider/chains/tfo.py
pathspider/chains/udp.py
pathspider/cmd/__init__.py
pathspider/cmd/analyse.py
pathspider/cmd/base.py
pathspider/cmd/filter.py
pathspider/cmd/measure.py
pathspider/cmd/observe.py
pathspider/cmd/report.py
pathspider/cmd/test.py
pathspider/helpers/__init__.py
pathspider/helpers/dns.py
pathspider/helpers/http.py
pathspider/helpers/tcp.py
pathspider/helpers/tor_http.py
pathspider/network/__init__.py
pathspider/plugins/__init__.py
pathspider/plugins/dnsresolv.py
pathspider/plugins/dscp.py
pathspider/plugins/ecn.py
pathspider/plugins/evilbit.py
pathspider/plugins/h2.py
pathspider/plugins/mss.py
pathspider/plugins/udpzero.py
pathspider/targets/__init__.py
pathspider/tests/data/basic_ipv4_non_udp_tcp.pcap
pathspider/tests/data/basic_ipv4_tcp.pcap
pathspider/tests/data/basic_ipv4_udp.pcap
pathspider/tests/data/basic_ipv6_tcp.pcap
pathspider/tests/data/basic_ipv6_udp.pcap
pathspider/tests/data/dns_no_response.pcap
pathspider/tests/data/dns_valid_response.pcap
pathspider/tests/data/dns_valid_response_tcp.pcap
pathspider/tests/data/dnsresolvtest.csv
pathspider/tests/data/dscp_ipv6_tcp_fwd3.pcap
pathspider/tests/data/dscp_tcp_allzero.pcap
pathspider/tests/data/dscp_tcp_fwd3.pcap
pathspider/tests/data/dscp_udp_allzero.pcap
pathspider/tests/data/dscp_udp_fwd3.pcap
pathspider/tests/data/ecn_fake_fwd_ce.pcap
pathspider/tests/data/ecn_fake_fwd_ect1.pcap
pathspider/tests/data/ecn_ipv4_nice_ect0.pcap
