Metadata-Version: 1.1
Name: pathspider
Version: 2.0.1
Summary: A tool for measuring path transparency in the Internet
Home-page: https://pathspider.net/
Author: Iain Learmonth
Author-email: irl@fsfe.org
License: GNU GPLv2
Keywords: internet measurement ecn tfo dns web www analysis router congestion path transparency latency diffserv dscp
Platform: UNKNOWN
Classifier: Development Status :: 5 - Production/Stable
Classifier: Environment :: Console
Classifier: Intended Audience :: Science/Research
Classifier: Topic :: Communications
Classifier: Topic :: Internet
Classifier: License :: OSI Approved :: GNU General Public License v2 (GPLv2)
Classifier: Programming Language :: Python :: 3.5
Classifier: Programming Language :: Python :: 3.6
